jackmesh/__init__.py
jackmesh/jackmesh.py
jackmesh-0.3.1.dist-info/LICENSE
jackmesh-0.3.1.dist-info/METADATA
jackmesh-0.3.1.dist-info/WHEEL
jackmesh-0.3.1.dist-info/entry_points.txt
jackmesh-0.3.1.dist-info/RECORD
