Metadata-Version: 2.1
Name: jackmesh
Version: 0.3.1
Summary: Python-based utility for managing Jack audio server connections with simple TOML config files.
License: GNU GPL v3
Author: omnitonal.com
Requires-Python: >=3.11,<4.0
Classifier: License :: Other/Proprietary License
Classifier: Programming Language :: Python :: 3
Classifier: Programming Language :: Python :: 3.11
Requires-Dist: pyjacklib (>=0.1.1,<0.2.0)
Requires-Dist: toml (>=0.10.2,<0.11.0)
